html2image/__init__.py
html2image/cli.py
html2image/html2image.py
html2image/browsers/__init__.py
html2image/browsers/browser.py
html2image/browsers/chrome.py
html2image/browsers/chrome_cdp.py
html2image/browsers/chromium.py
html2image/browsers/edge.py
html2image/browsers/firefox.py
html2image/browsers/firefox_cdp.py
html2image/browsers/search_utils.py
html2image-2.0.6.dist-info/METADATA
html2image-2.0.6.dist-info/WHEEL
html2image-2.0.6.dist-info/entry_points.txt
html2image-2.0.6.dist-info/licenses/LICENSE
html2image-2.0.6.dist-info/RECORD
