Metadata-Version: 2.4
Name: html2image
Version: 2.0.6
Summary: Package acting as a wrapper around the headless mode of existing web browsers to generate images from URLs and from HTML+CSS strings or files.
Project-URL: Homepage, https://github.com/vgalin/html2image
Project-URL: Repository, https://github.com/vgalin/html2image
Project-URL: Issues, https://github.com/vgalin/html2image/issues
Project-URL: Changelog, https://github.com/vgalin/html2image/releases
Author: vgalin
License: MIT License
License-File: LICENSE
Keywords: chrome,chromium,chromium-browser,css,css to image,html,html to image,image,screenshot
Classifier: Development Status :: 5 - Production/Stable
Classifier: License :: OSI Approved :: MIT License
Classifier: Operating System :: MacOS
Classifier: Operating System :: Microsoft :: Windows
Classifier: Operating System :: POSIX :: Linux
Classifier: Programming Language :: Python :: 3 :: Only
Classifier: Programming Language :: Python :: 3.6
Classifier: Programming Language :: Python :: 3.7
Classifier: Programming Language :: Python :: 3.8
Classifier: Programming Language :: Python :: 3.9
Classifier: Programming Language :: Python :: 3.10
Classifier: Programming Language :: Python :: 3.11
Classifier: Programming Language :: Python :: 3.12
Classifier: Programming Language :: Python :: 3.13
Classifier: Topic :: Multimedia :: Graphics :: Graphics Conversion
Classifier: Topic :: Software Development :: User Interfaces
Classifier: Topic :: Utilities
Requires-Python: >=3.6
Requires-Dist: requests
Requires-Dist: websocket-client~=1.0
Provides-Extra: dev
Requires-Dist: build; extra == 'dev'
Requires-Dist: flake8; extra == 'dev'
Requires-Dist: pillow>=8.2.0; extra == 'dev'
Requires-Dist: pytest; extra == 'dev'
Requires-Dist: twine; extra == 'dev'
Provides-Extra: lint
Requires-Dist: flake8; extra == 'lint'
Provides-Extra: test
Requires-Dist: pillow>=8.2.0; extra == 'test'
Requires-Dist: pytest; extra == 'test'
